setup.cfg
setup.py
festar/__init__.py
festar/festar_context.py
festar.egg-info/PKG-INFO
festar.egg-info/SOURCES.txt
festar.egg-info/dependency_links.txt
festar.egg-info/entry_points.txt
festar.egg-info/top_level.txt
festar/_internal/__init__.py
festar/_internal/function_serialization.py
festar/_internal/sdk_decorators.py
festar/cli/__init__.py
festar/cli/cli.py
festar/framework/__init__.py
festar/framework/base_festar_object.py
festar/framework/configs.py
festar/framework/data_frame.py
festar/framework/data_source.py
festar/framework/entity.py
festar/framework/feature_view.py
festar/framework/transformation.py
src/__init__.py
src/tests/__init__.py