Metadata-Version: 1.0
Name: festar
Version: 0.1
Summary: festar: standard feature production framework
Home-page: UNKNOWN
Author: zhanghaoran03
Author-email: zhanghaoran03@baidu.com
License: UNKNOWN
Platform: UNKNOWN
